{
    "version": 3,
    "configurePresets": [
        {
            "name": "default",
            "generator": "Ninja",
            "binaryDir": "${sourceDir}/build/${presetName}",
            "hidden": true,
            "cacheVariables": {
                "CMAKE_TOOLCHAIN_FILE": "$env{VCPKG_ROOT}/scripts/buildsystems/vcpkg.cmake"
            }
        },
        {
            "name": "debug",
            "inherits": [
                "default"
            ],
            "hidden": true,
            "cacheVariables": {
                "CMAKE_BUILD_TYPE": "Debug"
            }
        },
        {
            "name": "release",
            "inherits": [
                "default"
            ],
            "hidden": true,
            "cacheVariables": {
                "CMAKE_BUILD_TYPE": "Release",
                "CMAKE_INTERPROCEDURAL_OPTIMIZATION": "ON"
            }
        },
        {
            "name": "sanitize",
            "inherits": [
                "debug"
            ],
            "hidden": true,
            "cacheVariables": {
                "SAGE_WITH_ASAN": "ON",
                "SAGE_WITH_UBSAN": "ON"
            }
        },
        {
            "name": "macos-arm64-debug",
            "inherits": [
                "debug"
            ],
            "condition": {
                "type": "equals",
                "lhs": "${hostSystemName}",
                "rhs": "Darwin"
            },
            "cacheVariables": {
                "VCPKG_TARGET_TRIPLET": "arm64-osx-dynamic"
            }
        },
        {
            "name": "linux-x64-debug",
            "inherits": [
                "debug"
            ],
            "condition": {
                "type": "equals",
                "lhs": "${hostSystemName}",
                "rhs": "Linux"
            },
            "cacheVariables": {
                "VCPKG_TARGET_TRIPLET": "x64-linux-dynamic"
            }
        },
        {
            "name": "linux-x64-release",
            "inherits": [
                "release"
            ],
            "condition": {
                "type": "equals",
                "lhs": "${hostSystemName}",
                "rhs": "Linux"
            },
            "cacheVariables": {
                "VCPKG_TARGET_TRIPLET": "x64-linux-dynamic"
            }
        },
        {
            "name": "linux-x64-sanitize",
            "inherits": [
                "sanitize"
            ],
            "condition": {
                "type": "equals",
                "lhs": "${hostSystemName}",
                "rhs": "Linux"
            },
            "cacheVariables": {
                "VCPKG_TARGET_TRIPLET": "x64-linux-dynamic"
            }
        }
    ]
}